sungen/.github/workflows/python.yml
sungen/.gitignore
sungen/.gitlab-ci.yml
sungen/.openapi-generator-ignore
sungen/.travis.yml
sungen/README.md
sungen/__init__.py
sungen/api.py
sungen/auto_command.py
sungen/auto_router.py
sungen/auto_signature_route.py
sungen/cli.py
sungen/cmds/__init__.py
sungen/cmds/api_cmd.py
sungen/cmds/assist_cmd.py
sungen/cmds/branch_cmd.py
sungen/cmds/cmd_cmd.py
sungen/cmds/command_context.py
sungen/cmds/config_cmd.py
sungen/cmds/context_cmd.py
sungen/cmds/deploy_cmd.py
sungen/cmds/fgn_cmd.py
sungen/cmds/inhabitant_cmd.py
sungen/cmds/issue_cmd.py
sungen/cmds/llm_cmd.py
sungen/cmds/meta_cmd.py
sungen/cmds/optimize_cmd.py
sungen/cmds/pln_cmd.py
sungen/cmds/plugin_cmd.py
sungen/cmds/pr_cmd.py
sungen/cmds/project_cmd.py
sungen/cmds/proposal_cmd.py
sungen/cmds/repo_cmd.py
sungen/cmds/support_cmd.py
sungen/cmds/templates_cmd.py
sungen/cmds/ticket_cmd.py
sungen/config.yaml
sungen/dsl/__init__.py
sungen/dsl/dsl_dspy_assertion.py
sungen/dsl/dsl_pipeline_executor.py
sungen/dsl/dsl_predict_module.py
sungen/dsl/dsl_pydantic_models.py
sungen/dsl/dsl_step_module.py
sungen/dsl/examples/blog_pipeline.yaml
sungen/dsl/examples/example_pipeline.yaml
sungen/dsl/examples/poem_pipeline.yaml
sungen/dsl/examples/saltcorn_plugin_generator.yaml
sungen/dsl/examples/sql_to_nl.yaml
sungen/dsl/examples/text_signature_pipeline.yaml
sungen/dsl/modules/raw_to_structure_module.yaml
sungen/dsl/signature/sql_to_natural_signature.yaml
sungen/dsl/utils/__init__.py
sungen/dsl/utils/dsl_assertions_utils.py
sungen/dsl/utils/dsl_language_model_utils.py
sungen/dsl/utils/dsl_lm_module_utils.py
sungen/dsl/utils/dsl_retrieval_model_utils.py
sungen/dsl/utils/dsl_rm_module_utils.py
sungen/dsl/utils/dsl_signature_utils.py
sungen/dspy_modules/__init__.py
sungen/dspy_modules/ask_data_module.py
sungen/dspy_modules/ask_df_module.py
sungen/dspy_modules/df_sql_module.py
sungen/dspy_modules/file_name_module.py
sungen/dspy_modules/gen_cli_module.py
sungen/dspy_modules/gen_pydantic_instance.py
sungen-2024.10.15.dist-info/LICENSE
sungen-2024.10.15.dist-info/METADATA
sungen-2024.10.15.dist-info/WHEEL
sungen-2024.10.15.dist-info/entry_points.txt
sungen-2024.10.15.dist-info/RECORD
