Metadata-Version: 2.1
Name: sungen
Version: 2024.10.15
Summary: TODO
Home-page: https://github.com/seanchatmangpt/sungen
Author: Sean Chatman
Author-email: info@chatmangpt.com
Requires-Python: >=3.12,<3.13
Classifier: Programming Language :: Python :: 3
Classifier: Programming Language :: Python :: 3.12
Requires-Dist: asyncer (>=0.0.7,<0.0.8)
Requires-Dist: beautifulsoup4 (>=4.12.3,<5.0.0)
Requires-Dist: coloredlogs (>=15.0.1)
Requires-Dist: confz (>=2.0.1,<3.0.0)
Requires-Dist: docx (>=0.2.4,<0.3.0)
Requires-Dist: dslmodel (==2024.10.15)
Requires-Dist: dspy-ai (>=2.5.2,<3.0.0)
Requires-Dist: ebooklib (>=0.18,<0.19)
Requires-Dist: factory-boy (>=3.3.0,<4.0.0)
Requires-Dist: faker (>=26.0.0,<27.0.0)
Requires-Dist: fastapi[all] (>=0.110.1)
Requires-Dist: gunicorn (>=21.2.0)
Requires-Dist: icontract (>=2.6.6,<3.0.0)
Requires-Dist: ijson (>=3.3.0,<4.0.0)
Requires-Dist: inflection (>=0.5.1,<0.6.0)
Requires-Dist: inject (>=5.2.1,<6.0.0)
Requires-Dist: jinja2-ext (>=0.1,<0.2)
Requires-Dist: jinja2-time (>=0.2.0,<0.3.0)
Requires-Dist: jsonschema (>=4.22.0,<5.0.0)
Requires-Dist: loguru (>=0.7.2,<0.8.0)
Requires-Dist: munch (>=4.0.0,<5.0.0)
Requires-Dist: pandasql (>=0.7.3,<0.8.0)
Requires-Dist: poethepoet (>=0.25.0)
Requires-Dist: pygithub (>=2.3.0,<3.0.0)
Requires-Dist: pylint (>=3.2.7,<4.0.0)
Requires-Dist: pypdf (>=4.3.1,<5.0.0)
Requires-Dist: pyperclip (>=1.9.0,<2.0.0)
Requires-Dist: pytest-mock (>=3.14.0,<4.0.0)
Requires-Dist: pytest-watch (>=4.2.0,<5.0.0)
Requires-Dist: python-dotenv (>=1.0.1,<2.0.0)
Requires-Dist: speechrecognition (>=3.10.4,<4.0.0)
Requires-Dist: tiktoken (>=0.7.0,<0.8.0)
Requires-Dist: typer[all] (>=0.12.0)
Requires-Dist: uuid-utils (>=0.9.0,<0.10.0)
Requires-Dist: uvicorn[standard] (>=0.29.0)
Project-URL: Repository, https://github.com/seanchatmangpt/sungen
